ASYNC_FIFO.v
`timescale 1ns/1ns

module async_fifo
#(
  parameter DATA_WIDTH    = 16,
  parameter FIFO_DEPTH    = 8,               
  parameter ADDR_WIDTH    = 3                 
)
(
  // 复位信号
  input  wire                      wr_rst_n,
  input  wire                      rd_rst_n,

  // 写接口
  input  wire                      wr_clk,
  input  wire                      wr_en,
  input  wire    [DATA_WIDTH-1:0]  wr_data,

  // 读接口
  input  wire                      rd_clk,
  input  wire                      rd_en,
  output reg     [DATA_WIDTH-1:0]  rd_data,

  // 状态标志
  output wire                       full,
  output wire                      empty
);


reg [DATA_WIDTH-1:0] memory [0:FIFO_DEPTH-1];

// 写指针
reg  [ADDR_WIDTH:0] wr_ptr;
wire [ADDR_WIDTH:0] wr_ptr_gray;
reg  [ADDR_WIDTH:0] wr_ptr_gray_sync1;
reg  [ADDR_WIDTH:0] wr_ptr_gray_sync2;

// 读指针
reg  [ADDR_WIDTH:0] rd_ptr;
wire [ADDR_WIDTH:0] rd_ptr_gray;
reg  [ADDR_WIDTH:0] rd_ptr_gray_sync1;
reg  [ADDR_WIDTH:0] rd_ptr_gray_sync2;

// 地址
wire [ADDR_WIDTH-1:0] wr_addr;
wire [ADDR_WIDTH-1:0] rd_addr;


always @(posedge wr_clk or negedge wr_rst_n) begin
  if (!wr_rst_n) begin
    wr_ptr <= 0;
  end
  else if (wr_en && !full) begin
    wr_ptr <= wr_ptr + 1;
  end
end


assign wr_ptr_gray = wr_ptr ^ (wr_ptr >> 1);

// 同步到读时钟域
always @(posedge rd_clk or negedge rd_rst_n) begin
  if (!rd_rst_n) begin
    wr_ptr_gray_sync1 <= 0;
    wr_ptr_gray_sync2 <= 0;
  end
  else begin
    wr_ptr_gray_sync1 <= wr_ptr_gray;
    wr_ptr_gray_sync2 <= wr_ptr_gray_sync1;
  end
end


always @(posedge rd_clk or negedge rd_rst_n) begin
  if (!rd_rst_n) begin
    rd_ptr <= 0;
  end
  else if (rd_en && !empty) begin
    rd_ptr <= rd_ptr + 1;
  end
end

// 二进制转格雷码
assign rd_ptr_gray = rd_ptr ^ (rd_ptr >> 1);


always @(posedge wr_clk or negedge wr_rst_n) begin
  if (!wr_rst_n) begin
    rd_ptr_gray_sync1 <= 0;
    rd_ptr_gray_sync2 <= 0;
  end
  else begin
    rd_ptr_gray_sync1 <= rd_ptr_gray;
    rd_ptr_gray_sync2 <= rd_ptr_gray_sync1;
  end
end


assign full = ((wr_ptr_gray[ADDR_WIDTH] != rd_ptr_gray_sync2[ADDR_WIDTH]) &&
             (wr_ptr_gray[ADDR_WIDTH-1] != rd_ptr_gray_sync2[ADDR_WIDTH-1]) &&
             (wr_ptr_gray[ADDR_WIDTH-2:0] == rd_ptr_gray_sync2[ADDR_WIDTH-2:0]));



assign    empty = (rd_ptr_gray == wr_ptr_gray_sync2);



assign wr_addr = wr_ptr[ADDR_WIDTH-1:0];
assign rd_addr = rd_ptr[ADDR_WIDTH-1:0];


always @(posedge wr_clk) begin
  if (wr_en && !full) begin
    memory[wr_addr] <= wr_data;
  end
end


always @(posedge rd_clk or negedge rd_rst_n) begin
  if (!rd_rst_n) begin
    rd_data <= 0;
  end
  else if (rd_en && !empty) begin
    rd_data <= memory[rd_addr];
  end
end

endmodule

TB_ASYNC_FIFO.v
`timescale 1ns/1ns

module TB_ASYNC_FIFO;

  reg wr_rst_n, rd_rst_n;
  reg wr_clk, rd_clk;
  reg wr_en, rd_en;
  reg [15:0] wr_data;
  wire [15:0] rd_data;
  wire full, empty;

  async_fifo dut (
    .wr_rst_n(wr_rst_n),
    .rd_rst_n(rd_rst_n),
    .wr_clk(wr_clk),
    .wr_en(wr_en),
    .wr_data(wr_data),
    .rd_clk(rd_clk),
    .rd_en(rd_en),
    .rd_data(rd_data),
    .full(full),
    .empty(empty)
  );

  // 时钟
  always #5 wr_clk = ~wr_clk;
  always #7 rd_clk = ~rd_clk;

  integer i;
  initial begin
    // 初始化
    wr_clk = 0; rd_clk = 0;
    wr_rst_n = 0; rd_rst_n = 0;
    wr_en = 0; rd_en = 0;
    wr_data = 0;
    
    #100;
    wr_rst_n = 1; rd_rst_n = 1;
    #100;

    // 测试1：写4个数据
    $display("Writing 4 data...");
    for (i = 0; i < 8; i = i + 1) begin
      @(posedge wr_clk);
      wr_en = 1;
      wr_data = i + 100;
      #1;
      @(posedge wr_clk);
      wr_en = 0;
      #1;

    end
    // 测试2：读4个数据
    $display("Reading 4 data...");
    for (i = 0; i < 8; i = i + 1) begin
      @(posedge rd_clk);
      rd_en = 1;
      #1;
      $display("Read %0d: %d", i, rd_data);
      @(posedge rd_clk);
      rd_en = 0;
      #1;
    end

    $display("Test completed!");
    #100;
    $finish;
  end

  initial begin
    $dumpfile("wave.vcd");
    $dumpvars(0, TB_ASYNC_FIFO);
  end

endmodule

wave.vcd
$date
	Tue Aug 26 01:07:11 2025
$end
$version
	Icarus Verilog
$end
$timescale
	1ns
$end
$scope module TB_ASYNC_FIFO $end
$var wire 16 ! rd_data [15:0] $end
$var wire 1 " full $end
$var wire 1 # empty $end
$var reg 1 $ rd_clk $end
$var reg 1 % rd_en $end
$var reg 1 & rd_rst_n $end
$var reg 1 ' wr_clk $end
$var reg 16 ( wr_data [15:0] $end
$var reg 1 ) wr_en $end
$var reg 1 * wr_rst_n $end
$var integer 32 + i [31:0] $end
$scope module dut $end
$var wire 1 " full $end
$var wire 1 $ rd_clk $end
$var wire 1 % rd_en $end
$var wire 4 , rd_ptr_gray [3:0] $end
$var wire 1 & rd_rst_n $end
$var wire 1 ' wr_clk $end
$var wire 16 - wr_data [15:0] $end
$var wire 1 ) wr_en $end
$var wire 4 . wr_ptr_gray [3:0] $end
$var wire 1 * wr_rst_n $end
$var wire 3 / wr_addr [2:0] $end
$var wire 3 0 rd_addr [2:0] $end
$var wire 1 # empty $end
$var reg 16 1 rd_data [15:0] $end
$var reg 4 2 rd_ptr [3:0] $end
$var reg 4 3 rd_ptr_gray_sync1 [3:0] $end
$var reg 4 4 rd_ptr_gray_sync2 [3:0] $end
$var reg 4 5 wr_ptr [3:0] $end
$var reg 4 6 wr_ptr_gray_sync1 [3:0] $end
$var reg 4 7 wr_ptr_gray_sync2 [3:0] $end
$upscope $end
$upscope $end
$enddefinitions $end
#0
$dumpvars
b0 7
b0 6
b0 5
b0 4
b0 3
b0 2
b0 1
b0 0
b0 /
b0 .
b0 -
b0 ,
bx +
0*
0)
b0 (
0'
0&
0%
0$
1#
0"
b0 !
$end
#5
1'
#7
1$
#10
0'
#14
0$
#15
1'
#20
0'
#21
1$
#25
1'
#28
0$
#30
0'
#35
1'
1$
#40
0'
#42
0$
#45
1'
#49
1$
#50
0'
#55
1'
#56
0$
#60
0'
#63
1$
#65
1'
#70
0'
0$
#75
1'
#77
1$
#80
0'
#84
0$
#85
1'
#90
0'
#91
1$
#95
1'
#98
0$
#100
0'
1&
1*
#105
1'
1$
#110
0'
#112
0$
#115
1'
#119
1$
#120
0'
#125
1'
#126
0$
#130
0'
#133
1$
#135
1'
#140
0'
0$
#145
1'
#147
1$
#150
0'
#154
0$
#155
1'
#160
0'
#161
1$
#165
1'
#168
0$
#170
0'
#175
1'
1$
#180
0'
#182
0$
#185
1'
#189
1$
#190
0'
#195
1'
#196
0$
#200
0'
b0 +
#203
1$
#205
b1100100 (
b1100100 -
1)
1'
#210
0'
0$
#215
b1 /
b1 .
b1 5
0)
1'
#216
b1 +
#217
b1 6
1$
#220
0'
#224
0$
#225
b1100101 (
b1100101 -
1)
1'
#230
0'
#231
0#
b1 7
1$
#235
b10 /
b11 .
b10 5
0)
1'
#236
b10 +
#238
0$
#240
0'
#245
b11 6
b1100110 (
b1100110 -
1)
1'
1$
#250
0'
#252
0$
#255
b11 /
b10 .
b11 5
0)
1'
#256
b11 +
#259
b11 7
b10 6
1$
#260
0'
#265
b1100111 (
b1100111 -
1)
1'
#266
0$
#270
0'
#273
b10 7
1$
#275
b100 /
b110 .
b100 5
0)
1'
#276
b100 +
#280
0'
0$
#285
b1101000 (
b1101000 -
1)
1'
#287
b110 6
1$
#290
0'
#294
0$
#295
b101 /
b111 .
b101 5
0)
1'
#296
b101 +
#300
0'
#301
b110 7
b111 6
1$
#305
b1101001 (
b1101001 -
1)
1'
#308
0$
#310
0'
#315
b110 /
b101 .
b110 5
b111 7
0)
1'
1$
#316
b110 +
#320
0'
#322
0$
#325
b1101010 (
b1101010 -
1)
1'
#329
b101 6
1$
#330
0'
#335
b111 /
b100 .
b111 5
0)
1'
#336
b111 +
0$
#340
0'
#343
b101 7
b100 6
1$
#345
b1101011 (
b1101011 -
1)
1'
#350
0'
0$
#355
1"
b0 /
b1100 .
b1000 5
0)
1'
#356
b0 +
#357
b1 0
b1 ,
b100 7
b1100 6
b1 2
b1100100 !
b1100100 1
1%
1$
#360
0'
#364
0$
#365
b1 3
1'
#370
0'
#371
b1100 7
0%
1$
#372
b1 +
#375
0"
b1 4
1'
#378
0$
#380
0'
#385
b10 0
b11 ,
b10 2
b1100101 !
b1100101 1
1%
1'
1$
#390
0'
#392
0$
#395
b11 3
1'
#399
0%
1$
#400
b10 +
0'
#405
b11 4
1'
#406
0$
#410
0'
#413
b11 0
b10 ,
b11 2
b1100110 !
b1100110 1
1%
1$
#415
b10 3
1'
#420
0'
0$
#425
b10 4
1'
#427
0%
1$
#428
b11 +
#430
0'
#434
0$
#435
1'
#440
0'
#441
b100 0
b110 ,
b100 2
b1100111 !
b1100111 1
1%
1$
#445
b110 3
1'
#448
0$
#450
0'
#455
b110 4
0%
1'
1$
#456
b100 +
#460
0'
#462
0$
#465
1'
#469
b101 0
b111 ,
b101 2
b1101000 !
b1101000 1
1%
1$
#470
0'
#475
b111 3
1'
#476
0$
#480
0'
#483
0%
1$
#484
b101 +
#485
b111 4
1'
#490
0'
0$
#495
1'
#497
b110 0
b101 ,
b110 2
b1101001 !
b1101001 1
1%
1$
#500
0'
#504
0$
#505
b101 3
1'
#510
0'
#511
0%
1$
#512
b110 +
#515
b101 4
1'
#518
0$
#520
0'
#525
b111 0
b100 ,
b111 2
b1101010 !
b1101010 1
1%
1'
1$
#530
0'
#532
0$
#535
b100 3
1'
#539
0%
1$
#540
b111 +
0'
#545
b100 4
1'
#546
0$
#550
0'
#553
1#
b0 0
b1100 ,
b1000 2
b1101011 !
b1101011 1
1%
1$
#555
b1100 3
1'
#560
0'
0$
#565
b1100 4
1'
#567
0%
1$
#568
b1000 +
