ASYNC_FIFO.v
`timescale 1ns/1ns

module async_fifo
#(
  parameter DATA_WIDTH    = 16,
  parameter FIFO_DEPTH    = 8,
  parameter PTR_WIDTH     = 4,                // log2(FIFO_DEPTH) + 1
  parameter ADDR_WIDTH    = 3                 // log2(FIFO_DEPTH)
)
(
  // 复位信号
  input  wire                      wr_rst_n,
  input  wire                      rd_rst_n,

  // 写接口
  input  wire                      wr_clk,
  input  wire                      wr_en,
  input  wire    [DATA_WIDTH-1:0]  wr_data,

  // 读接口
  input  wire                      rd_clk,
  input  wire                      rd_en,
  output reg     [DATA_WIDTH-1:0]  rd_data,

  // 状态标志
  output reg                       full,
  output reg                       empty
);

// 存储器阵列
reg [DATA_WIDTH-1:0] memory [0:FIFO_DEPTH-1];

// 写指针
reg  [PTR_WIDTH-1:0] wr_ptr;
wire [PTR_WIDTH-1:0] wr_ptr_gray;
reg  [PTR_WIDTH-1:0] wr_ptr_gray_sync1;
reg  [PTR_WIDTH-1:0] wr_ptr_gray_sync2;

// 读指针
reg  [PTR_WIDTH-1:0] rd_ptr;
wire [PTR_WIDTH-1:0] rd_ptr_gray;
reg  [PTR_WIDTH-1:0] rd_ptr_gray_sync1;
reg  [PTR_WIDTH-1:0] rd_ptr_gray_sync2;

// 地址
wire [ADDR_WIDTH-1:0] wr_addr;
wire [ADDR_WIDTH-1:0] rd_addr;

// ==================== 写指针逻辑 ====================
always @(posedge wr_clk or negedge wr_rst_n) begin
  if (!wr_rst_n) begin
    wr_ptr <= 0;
  end
  else if (wr_en && !full) begin
    wr_ptr <= wr_ptr + 1;
  end
end

// 二进制转格雷码
assign wr_ptr_gray = wr_ptr ^ (wr_ptr >> 1);

// 同步到读时钟域
always @(posedge rd_clk or negedge rd_rst_n) begin
  if (!rd_rst_n) begin
    wr_ptr_gray_sync1 <= 0;
    wr_ptr_gray_sync2 <= 0;
  end
  else begin
    wr_ptr_gray_sync1 <= wr_ptr_gray;
    wr_ptr_gray_sync2 <= wr_ptr_gray_sync1;
  end
end

// ==================== 读指针逻辑 ====================
always @(posedge rd_clk or negedge rd_rst_n) begin
  if (!rd_rst_n) begin
    rd_ptr <= 0;
  end
  else if (rd_en && !empty) begin
    rd_ptr <= rd_ptr + 1;
  end
end

// 二进制转格雷码
assign rd_ptr_gray = rd_ptr ^ (rd_ptr >> 1);

// 同步到写时钟域
always @(posedge wr_clk or negedge wr_rst_n) begin
  if (!wr_rst_n) begin
    rd_ptr_gray_sync1 <= 0;
    rd_ptr_gray_sync2 <= 0;
  end
  else begin
    rd_ptr_gray_sync1 <= rd_ptr_gray;
    rd_ptr_gray_sync2 <= rd_ptr_gray_sync1;
  end
end

// ==================== 空满标志 ====================
// 满标志：写指针比读指针多一圈
wire [PTR_WIDTH-1:0] rd_ptr_bin_sync;
// 格雷码转二进制（同步后的读指针）
assign rd_ptr_bin_sync[PTR_WIDTH-1] = rd_ptr_gray_sync2[PTR_WIDTH-1];
generate
  genvar k;
  for (k = PTR_WIDTH-2; k >= 0; k = k-1) begin
    assign rd_ptr_bin_sync[k] = rd_ptr_bin_sync[k+1] ^ rd_ptr_gray_sync2[k];
  end
endgenerate

always @(posedge wr_clk or negedge wr_rst_n) begin
  if (!wr_rst_n) begin
    full <= 0;
  end
  else begin
    full <= ((wr_ptr - rd_ptr_bin_sync) >= FIFO_DEPTH);
  end
end

// 空标志：读写指针相等
always @(posedge rd_clk or negedge rd_rst_n) begin
  if (!rd_rst_n) begin
    empty <= 1;
  end
  else begin
    empty <= (rd_ptr == wr_ptr_gray_sync2);
  end
end

// ==================== 地址生成 ====================
assign wr_addr = wr_ptr[ADDR_WIDTH-1:0];
assign rd_addr = rd_ptr[ADDR_WIDTH-1:0];

// ==================== 写操作 ====================
always @(posedge wr_clk) begin
  if (wr_en && !full) begin
    memory[wr_addr] <= wr_data;
  end
end

// ==================== 读操作 ====================
always @(posedge rd_clk or negedge rd_rst_n) begin
  if (!rd_rst_n) begin
    rd_data <= 0;
  end
  else if (rd_en && !empty) begin
    rd_data <= memory[rd_addr];
  end
end

endmodule

TB_ASYNC_FIFO.v
`timescale 1ns/1ns

module TB_ASYNC_FIFO;

  reg wr_rst_n, rd_rst_n;
  reg wr_clk, rd_clk;
  reg wr_en, rd_en;
  reg [15:0] wr_data;
  wire [15:0] rd_data;
  wire full, empty;

  async_fifo dut (
    .wr_rst_n(wr_rst_n),
    .rd_rst_n(rd_rst_n),
    .wr_clk(wr_clk),
    .wr_en(wr_en),
    .wr_data(wr_data),
    .rd_clk(rd_clk),
    .rd_en(rd_en),
    .rd_data(rd_data),
    .full(full),
    .empty(empty)
  );

  // 时钟
  always #5 wr_clk = ~wr_clk;
  always #7 rd_clk = ~rd_clk;

  integer i;
  initial begin
    // 初始化
    wr_clk = 0; rd_clk = 0;
    wr_rst_n = 0; rd_rst_n = 0;
    wr_en = 0; rd_en = 0;
    wr_data = 0;
    
    #100;
    wr_rst_n = 1; rd_rst_n = 1;
    #100;

    // 测试1：写4个数据
    $display("Writing 4 data...");
    for (i = 0; i < 4; i = i + 1) begin
      @(posedge wr_clk);
      wr_en = 1;
      wr_data = i + 100;
      #1;
    end
    @(posedge wr_clk);
    wr_en = 0;
    #200; // 等待足够时间同步

    // 测试2：读4个数据
    $display("Reading 4 data...");
    for (i = 0; i < 4; i = i + 1) begin
      @(posedge rd_clk);
      rd_en = 1;
      #1;
      $display("Read %0d: %d", i, rd_data);
      @(posedge rd_clk);
      rd_en = 0;
      #1;
    end

    $display("Test completed!");
    #100;
    $finish;
  end

  initial begin
    $dumpfile("wave.vcd");
    $dumpvars(0, TB_ASYNC_FIFO);
  end

endmodule

wave.vcd
$date
	Sun Aug 24 23:00:21 2025
$end
$version
	Icarus Verilog
$end
$timescale
	1ns
$end
$scope module TB_ASYNC_FIFO $end
$var wire 16 ! rd_data [15:0] $end
$var wire 1 " full $end
$var wire 1 # empty $end
$var reg 1 $ rd_clk $end
$var reg 1 % rd_en $end
$var reg 1 & rd_rst_n $end
$var reg 1 ' wr_clk $end
$var reg 16 ( wr_data [15:0] $end
$var reg 1 ) wr_en $end
$var reg 1 * wr_rst_n $end
$var integer 32 + i [31:0] $end
$scope module dut $end
$var wire 1 $ rd_clk $end
$var wire 1 % rd_en $end
$var wire 4 , rd_ptr_gray [3:0] $end
$var wire 1 & rd_rst_n $end
$var wire 1 ' wr_clk $end
$var wire 16 - wr_data [15:0] $end
$var wire 1 ) wr_en $end
$var wire 4 . wr_ptr_gray [3:0] $end
$var wire 1 * wr_rst_n $end
$var wire 3 / wr_addr [2:0] $end
$var wire 4 0 rd_ptr_bin_sync [3:0] $end
$var wire 3 1 rd_addr [2:0] $end
$var reg 1 # empty $end
$var reg 1 " full $end
$var reg 16 2 rd_data [15:0] $end
$var reg 4 3 rd_ptr [3:0] $end
$var reg 4 4 rd_ptr_gray_sync1 [3:0] $end
$var reg 4 5 rd_ptr_gray_sync2 [3:0] $end
$var reg 4 6 wr_ptr [3:0] $end
$var reg 4 7 wr_ptr_gray_sync1 [3:0] $end
$var reg 4 8 wr_ptr_gray_sync2 [3:0] $end
$scope begin genblk1[0] $end
$upscope $end
$scope begin genblk1[1] $end
$upscope $end
$scope begin genblk1[2] $end
$upscope $end
$upscope $end
$upscope $end
$enddefinitions $end
#0
$dumpvars
b0 8
b0 7
b0 6
b0 5
b0 4
b0 3
b0 2
b0 1
b0 0
b0 /
b0 .
b0 -
b0 ,
bx +
0*
0)
b0 (
0'
0&
0%
0$
1#
0"
b0 !
$end
#5
1'
#7
1$
#10
0'
#14
0$
#15
1'
#20
0'
#21
1$
#25
1'
#28
0$
#30
0'
#35
1'
1$
#40
0'
#42
0$
#45
1'
#49
1$
#50
0'
#55
1'
#56
0$
#60
0'
#63
1$
#65
1'
#70
0'
0$
#75
1'
#77
1$
#80
0'
#84
0$
#85
1'
#90
0'
#91
1$
#95
1'
#98
0$
#100
0'
1&
1*
#105
1'
1$
#110
0'
#112
0$
#115
1'
#119
1$
#120
0'
#125
1'
#126
0$
#130
0'
#133
1$
#135
1'
#140
0'
0$
#145
1'
#147
1$
#150
0'
#154
0$
#155
1'
#160
0'
#161
1$
#165
1'
#168
0$
#170
0'
#175
1'
1$
#180
0'
#182
0$
#185
1'
#189
1$
#190
0'
#195
1'
#196
0$
#200
0'
b0 +
#203
1$
#205
b1100100 (
b1100100 -
1)
1'
#206
b1 +
#210
0'
0$
#215
b1 /
b1 .
b1 6
b1100101 (
b1100101 -
1'
#216
b10 +
#217
b1 7
1$
#220
0'
#224
0$
#225
b10 /
b11 .
b10 6
b1100110 (
b1100110 -
1'
#226
b11 +
#230
0'
#231
b1 8
b11 7
1$
#235
b11 /
b10 .
b11 6
b1100111 (
b1100111 -
1'
#236
b100 +
#238
0$
#240
0'
#245
b100 /
b110 .
b100 6
b11 8
b10 7
0#
0)
1'
1$
#250
0'
#252
0$
#255
1'
#259
b10 8
b110 7
1$
#260
0'
#265
1'
#266
0$
#270
0'
#273
b110 8
1$
