ASYNC_FIFO.v
`timescale 1ns/1ns

module async_fifo
#(
  parameter DATA_WIDTH    = 16,
  parameter FIFO_DEPTH    = 8,               
  parameter ADDR_WIDTH    = 3                 
)
(
  // 复位信号
  input  wire                      wr_rst_n,
  input  wire                      rd_rst_n,

  // 写接口
  input  wire                      wr_clk,
  input  wire                      wr_en,
  input  wire    [DATA_WIDTH-1:0]  wr_data,

  // 读接口
  input  wire                      rd_clk,
  input  wire                      rd_en,
  output reg     [DATA_WIDTH-1:0]  rd_data,

  // 状态标志
  output wire                       full,
  output wire                      empty
);


reg [DATA_WIDTH-1:0] memory [0:FIFO_DEPTH-1];

// 写指针
reg  [ADDR_WIDTH:0] wr_ptr;
wire [ADDR_WIDTH:0] wr_ptr_gray;
reg  [ADDR_WIDTH:0] wr_ptr_gray_sync1;
reg  [ADDR_WIDTH:0] wr_ptr_gray_sync2;

// 读指针
reg  [ADDR_WIDTH:0] rd_ptr;
wire [ADDR_WIDTH:0] rd_ptr_gray;
reg  [ADDR_WIDTH:0] rd_ptr_gray_sync1;
reg  [ADDR_WIDTH:0] rd_ptr_gray_sync2;

// 地址
wire [ADDR_WIDTH-1:0] wr_addr;
wire [ADDR_WIDTH-1:0] rd_addr;


always @(posedge wr_clk or negedge wr_rst_n) begin
  if (!wr_rst_n) begin
    wr_ptr <= 0;
  end
  else if (wr_en && !full) begin
    wr_ptr <= wr_ptr + 1;
  end
end


assign wr_ptr_gray = wr_ptr ^ (wr_ptr >> 1);

// 同步到读时钟域
always @(posedge rd_clk or negedge rd_rst_n) begin
  if (!rd_rst_n) begin
    wr_ptr_gray_sync1 <= 0;
    wr_ptr_gray_sync2 <= 0;
  end
  else begin
    wr_ptr_gray_sync1 <= wr_ptr_gray;
    wr_ptr_gray_sync2 <= wr_ptr_gray_sync1;
  end
end


always @(posedge rd_clk or negedge rd_rst_n) begin
  if (!rd_rst_n) begin
    rd_ptr <= 0;
  end
  else if (rd_en && !empty) begin
    rd_ptr <= rd_ptr + 1;
  end
end

// 二进制转格雷码
assign rd_ptr_gray = rd_ptr ^ (rd_ptr >> 1);


always @(posedge wr_clk or negedge wr_rst_n) begin
  if (!wr_rst_n) begin
    rd_ptr_gray_sync1 <= 0;
    rd_ptr_gray_sync2 <= 0;
  end
  else begin
    rd_ptr_gray_sync1 <= rd_ptr_gray;
    rd_ptr_gray_sync2 <= rd_ptr_gray_sync1;
  end
end


//assign full = ((wr_ptr_gray[ADDR_WIDTH] != rd_ptr_gray_sync2[ADDR_WIDTH]) &&
//              (wr_ptr_gray[ADDR_WIDTH-1] != rd_ptr_gray_sync2[ADDR_WIDTH-1]) &&
//              (wr_ptr_gray[ADDR_WIDTH-2:0] == rd_ptr_gray_sync2[ADDR_WIDTH-2:0]));

assign full = ((wr_ptr_gray[ADDR_WIDTH:ADDR_WIDTH-1]==~rd_ptr_gray_sync2[ADDR_WIDTH:ADDR_WIDTH-1])&&(wr_ptr_gray[1:0]==rd_ptr_gray_sync2[1:0]));

assign    empty = (rd_ptr_gray == wr_ptr_gray_sync2);



assign wr_addr = wr_ptr[ADDR_WIDTH-1:0];
assign rd_addr = rd_ptr[ADDR_WIDTH-1:0];


always @(posedge wr_clk or negedge wr_rst_n) begin

  if (wr_en && !full) begin
    memory[wr_addr] <= wr_data;
  end
end


always @(posedge rd_clk or negedge rd_rst_n) begin
  if (!rd_rst_n) begin
    rd_data <= 0;
  end
  else if (rd_en && !empty) begin
    rd_data <= memory[rd_addr];
  end
end

endmodule

TB_ASYNC_FIFO.v
`timescale 1ns/1ns

module TB_ASYNC_FIFO;

  reg wr_rst_n, rd_rst_n;
  reg wr_clk, rd_clk;
  reg wr_en, rd_en;
  reg [15:0] wr_data;
  wire [15:0] rd_data;
  wire full, empty;

  async_fifo dut (
    .wr_rst_n(wr_rst_n),
    .rd_rst_n(rd_rst_n),
    .wr_clk(wr_clk),
    .wr_en(wr_en),
    .wr_data(wr_data),
    .rd_clk(rd_clk),
    .rd_en(rd_en),
    .rd_data(rd_data),
    .full(full),
    .empty(empty)
  );

  // 时钟
  always #5 wr_clk = ~wr_clk;
  always #7 rd_clk = ~rd_clk;

  integer write_count = 0;
  integer read_count = 0;
  
  initial begin
    // 初始化
    wr_clk = 0; rd_clk = 0;
    wr_rst_n = 0; rd_rst_n = 0;
    wr_en = 0; rd_en = 0;
    wr_data = 0;
    
    #100;
    wr_rst_n = 1; rd_rst_n = 1;
    #100;

    $display("=== Starting交错读写测试 ===");
    $display("Time\tOperation\tData\t\tFull\tEmpty");
    $display("--------------------------------------------------");
    
   
    fork
      // 写进程：写入20个数据
      begin
        for (write_count = 0; write_count < 30; write_count = write_count + 1) begin
          @(posedge wr_clk);
          if (!full) begin
            wr_en = 1;
            wr_data = write_count + 100; 
            #1;
            $display("%0t\tWrite\t\t%4d\t\t%b\t%b", $time, wr_data, full, empty);
            @(posedge wr_clk);
            wr_en = 0;
            #1;
          end else begin
            $display("%0t\tWrite blocked\t-\t\t%b\t%b", $time, full, empty);
            #10; 
          end
        end
        $display("=== 写入完成 ===");
      end
      
      // 读进程：读取20个数据
      begin
        #50; 
        for (read_count = 0; read_count < 30; read_count = read_count + 1) begin
          @(posedge rd_clk);
          if (!empty) begin
            rd_en = 1;
            #1;
            $display("%0t\tRead\t\t%4d\t\t%b\t%b", $time, rd_data, full, empty);
            @(posedge rd_clk);
            rd_en = 0;
            #1;
          end else begin
            $display("%0t\tRead blocked\t-\t\t%b\t%b", $time, full, empty);
            #10; 
          end
        end
        $display("=== 读取完成 ===");
      end
    join

    
    $display("\n=== 测试边界条件 ===");
    
    
    $display("=== 尝试写满FIFO ===");
    while (!full) begin
      @(posedge wr_clk);
      wr_en = 1;
      wr_data = write_count + 100;
      write_count = write_count + 1;
      #1;
      $display("%0t\tWrite to full\t%4d\t\t%b\t%b", $time, wr_data, full, empty);
      @(posedge wr_clk);
      wr_en = 0;
      #1;
    end
    
 
    $display("=== 尝试读空FIFO ===");
    while (!empty) begin
      @(posedge rd_clk);
      rd_en = 1;
      #1;
      $display("%0t\tRead to empty\t%4d\t\t%b\t%b", $time, rd_data, full, empty);
      @(posedge rd_clk);
      rd_en = 0;
      #1;
    end

    $display("=== 测试完成! ===");
    #100;
    $finish;
  end

  initial begin
    $dumpfile("wave.vcd");
    $dumpvars(0, TB_ASYNC_FIFO);
    #2000; 
    $display("仿真超时!");
    $finish;
  end

  
  always @(posedge wr_clk) begin
    if (wr_en && full) begin
      $display("%0t\tERROR: 在满状态下写入!", $time);
    end
  end

  always @(posedge rd_clk) begin
    if (rd_en && empty) begin
      $display("%0t\tERROR: 在空状态下读取!", $time);
    end
  end

endmodule

wave.vcd
$date
	Tue Aug 26 21:51:12 2025
$end
$version
	Icarus Verilog
$end
$timescale
	1ns
$end
$scope module TB_ASYNC_FIFO $end
$var wire 16 ! rd_data [15:0] $end
$var wire 1 " full $end
$var wire 1 # empty $end
$var reg 1 $ rd_clk $end
$var reg 1 % rd_en $end
$var reg 1 & rd_rst_n $end
$var reg 1 ' wr_clk $end
$var reg 16 ( wr_data [15:0] $end
$var reg 1 ) wr_en $end
$var reg 1 * wr_rst_n $end
$var integer 32 + read_count [31:0] $end
$var integer 32 , write_count [31:0] $end
$scope module dut $end
$var wire 1 " full $end
$var wire 1 $ rd_clk $end
$var wire 1 % rd_en $end
$var wire 4 - rd_ptr_gray [3:0] $end
$var wire 1 & rd_rst_n $end
$var wire 1 ' wr_clk $end
$var wire 16 . wr_data [15:0] $end
$var wire 1 ) wr_en $end
$var wire 4 / wr_ptr_gray [3:0] $end
$var wire 1 * wr_rst_n $end
$var wire 3 0 wr_addr [2:0] $end
$var wire 3 1 rd_addr [2:0] $end
$var wire 1 # empty $end
$var reg 16 2 rd_data [15:0] $end
$var reg 4 3 rd_ptr [3:0] $end
$var reg 4 4 rd_ptr_gray_sync1 [3:0] $end
$var reg 4 5 rd_ptr_gray_sync2 [3:0] $end
$var reg 4 6 wr_ptr [3:0] $end
$var reg 4 7 wr_ptr_gray_sync1 [3:0] $end
$var reg 4 8 wr_ptr_gray_sync2 [3:0] $end
$upscope $end
$upscope $end
$enddefinitions $end
#0
$dumpvars
b0 8
b0 7
b0 6
b0 5
b0 4
b0 3
b0 2
b0 1
b0 0
b0 /
b0 .
b0 -
b0 ,
b0 +
0*
0)
b0 (
0'
0&
0%
0$
1#
0"
b0 !
$end
#5
1'
#7
1$
#10
0'
#14
0$
#15
1'
#20
0'
#21
1$
#25
1'
#28
0$
#30
0'
#35
1'
1$
#40
0'
#42
0$
#45
1'
#49
1$
#50
0'
#55
1'
#56
0$
#60
0'
#63
1$
#65
1'
#70
0'
0$
#75
1'
#77
1$
#80
0'
#84
0$
#85
1'
#90
0'
#91
1$
#95
1'
#98
0$
#100
0'
1&
1*
#105
1'
1$
#110
0'
#112
0$
#115
1'
#119
1$
#120
0'
#125
1'
#126
0$
#130
0'
#133
1$
#135
1'
#140
0'
0$
#145
1'
#147
1$
#150
0'
#154
0$
#155
1'
#160
0'
#161
1$
#165
1'
#168
0$
#170
0'
#175
1'
1$
#180
0'
#182
0$
#185
1'
#189
1$
#190
0'
#195
1'
#196
0$
#200
0'
#203
1$
#205
b1 0
b1 /
b1 6
b1100100 (
b1100100 .
1)
1'
#210
0'
0$
#215
0)
1'
#216
b1 ,
#217
b1 7
1$
#220
0'
#224
0$
#225
b10 0
b11 /
b10 6
b1100101 (
b1100101 .
1)
1'
#230
0'
#231
0#
b1 8
b11 7
1$
#235
0)
1'
#236
b10 ,
#238
0$
#240
0'
#245
b11 0
b10 /
b11 6
b11 8
b1100110 (
b1100110 .
1)
1'
1$
#250
0'
#252
0$
#255
0)
1'
#256
b11 ,
#259
b1 1
b1 -
b1100100 !
b1100100 2
b1 3
b10 7
1%
1$
#260
0'
#265
b100 0
b110 /
b1 4
b100 6
b1100111 (
b1100111 .
1)
1'
#266
0$
#270
0'
#273
b10 8
b110 7
0%
1$
#274
b1 +
#275
b1 5
0)
1'
#276
b100 ,
#280
0'
0$
#285
b101 0
b111 /
b101 6
b1101000 (
b1101000 .
1)
1'
#287
b10 1
b11 -
b1100101 !
b1100101 2
b10 3
b110 8
b111 7
1%
1$
#290
0'
#294
0$
#295
b11 4
0)
1'
#296
b101 ,
#300
0'
#301
b111 8
0%
1$
#302
b10 +
#305
b110 0
b101 /
b11 5
b110 6
b1101001 (
b1101001 .
1)
1'
#308
0$
#310
0'
#315
b11 1
b10 -
b1100110 !
b1100110 2
b11 3
b101 7
0)
1%
1'
1$
#316
b110 ,
#320
0'
#322
0$
#325
b111 0
b100 /
b10 4
b111 6
b1101010 (
b1101010 .
1)
1'
#329
b101 8
b100 7
0%
1$
#330
b11 +
0'
#335
b10 5
0)
1'
#336
b111 ,
0$
#340
0'
#343
b100 1
b110 -
b1100111 !
b1100111 2
b100 3
b100 8
1%
1$
#345
b0 0
b1100 /
b110 4
b1000 6
b1101011 (
b1101011 .
1)
1'
#350
0'
0$
#355
b110 5
0)
1'
#356
b1000 ,
#357
b1100 7
0%
1$
#358
b100 +
#360
0'
#364
0$
#365
b1 0
b1101 /
b1001 6
b1101100 (
b1101100 .
1)
1'
#370
0'
#371
b101 1
b111 -
b1101000 !
b1101000 2
b101 3
b1100 8
b1101 7
1%
1$
#375
b111 4
0)
1'
#376
b1001 ,
#378
0$
#380
0'
#385
b10 0
b1111 /
b111 5
b1010 6
b1101 8
b1101101 (
b1101101 .
1)
0%
1'
1$
#386
b101 +
#390
0'
#392
0$
#395
0)
1'
#396
b1010 ,
#399
b110 1
b101 -
b1101001 !
b1101001 2
b110 3
b1111 7
1%
1$
#400
0'
#405
b11 0
b1110 /
b101 4
b1011 6
b1101110 (
b1101110 .
1)
1'
#406
0$
#410
0'
#413
b1111 8
b1110 7
0%
1$
#414
b110 +
#415
b101 5
0)
1'
#416
b1011 ,
#420
0'
0$
#425
0"
b100 0
b1010 /
b1100 6
b1101111 (
b1101111 .
1)
1'
#427
b111 1
b100 -
b1101010 !
b1101010 2
b111 3
b1110 8
b1010 7
1%
1$
#430
0'
#434
0$
#435
b100 4
0)
1'
#436
b1100 ,
#440
0'
#441
b1010 8
0%
1$
#442
b111 +
#445
b101 0
b1011 /
b100 5
b1101 6
b1110000 (
b1110000 .
1)
1'
#448
0$
#450
0'
#455
b0 1
b1100 -
b1101011 !
b1101011 2
b1000 3
b1011 7
0)
1%
1'
1$
#456
b1101 ,
#460
0'
#462
0$
#465
0"
b110 0
b1001 /
b1100 4
b1110 6
b1110001 (
b1110001 .
1)
1'
#469
b1011 8
b1001 7
0%
1$
#470
b1000 +
0'
#475
b1100 5
0)
1'
#476
b1110 ,
0$
#480
0'
#483
b1 1
b1101 -
b1101100 !
b1101100 2
b1001 3
b1001 8
1%
1$
#485
b111 0
b1000 /
b1101 4
b1111 6
b1110010 (
b1110010 .
1)
1'
#490
0'
0$
#495
b1101 5
0)
1'
#496
b1111 ,
#497
b1000 7
0%
1$
#498
b1001 +
#500
0'
#504
0$
#505
b0 0
b0 /
b0 6
b1110011 (
b1110011 .
1)
1'
#510
0'
#511
b10 1
b1111 -
b1101101 !
b1101101 2
b1010 3
b1000 8
b0 7
1%
1$
#515
b1111 4
0)
1'
#516
b10000 ,
#518
0$
#520
0'
#525
b1 0
b1 /
b1111 5
b1 6
b0 8
b1110100 (
b1110100 .
1)
0%
1'
1$
#526
b1010 +
#530
0'
#532
0$
#535
0)
1'
#536
b10001 ,
#539
b11 1
b1110 -
b1101110 !
b1101110 2
b1011 3
b1 7
1%
1$
#540
0'
#545
1"
b10 0
b11 /
b1110 4
b10 6
b1110101 (
b1110101 .
1)
1'
#546
0$
#550
0'
#553
b1 8
b11 7
0%
1$
#554
b1011 +
#555
0"
b1110 5
0)
1'
#556
b10010 ,
#560
0'
0$
#565
1"
b11 0
b10 /
b11 6
b1110110 (
b1110110 .
1)
1'
#567
b100 1
b1010 -
b1101111 !
b1101111 2
b1100 3
b11 8
b10 7
1%
1$
#570
0'
#574
0$
#575
b1010 4
0)
1'
#576
b10011 ,
#580
0'
#581
b10 8
0%
1$
#582
b1100 +
#585
0"
b1010 5
1'
#588
0$
#590
0'
#595
1"
b100 0
b110 /
b101 1
b1011 -
b100 6
b1110000 !
b1110000 2
b1101 3
b1111000 (
b1111000 .
1)
1%
1'
1$
b10100 ,
#600
0'
#602
0$
#605
b1011 4
0)
1'
#606
b10101 ,
#609
b110 7
0%
1$
#610
b1101 +
0'
#615
0"
b1011 5
1'
#616
0$
#620
0'
#623
b110 1
b1001 -
b1110001 !
b1110001 2
b1110 3
b110 8
1%
1$
#625
1"
b101 0
b111 /
b1001 4
b101 6
b1111010 (
b1111010 .
1)
1'
b10110 ,
#630
0'
0$
#635
0"
b1001 5
0)
1'
#636
b10111 ,
#637
b111 7
0%
1$
#638
b1110 +
#640
0'
#644
0$
#645
1"
b110 0
b101 /
b110 6
b1111011 (
b1111011 .
1)
1'
#650
0'
#651
b111 1
b1000 -
b1110010 !
b1110010 2
b1111 3
b111 8
b101 7
1%
1$
#655
b1000 4
0)
1'
#656
b11000 ,
#658
0$
#660
0'
#665
0"
b1000 5
b101 8
0%
1'
1$
#666
b1111 +
#670
0'
#672
0$
#675
1"
b111 0
b100 /
b111 6
b1111101 (
b1111101 .
1)
1'
b11001 ,
#679
b0 1
b0 -
b1110011 !
b1110011 2
b0 3
b100 7
1%
1$
#680
0'
#685
b0 4
0)
1'
#686
b11010 ,
0$
#690
0'
#693
b100 8
0%
1$
#694
b10000 +
#695
0"
b0 5
1'
#700
0'
0$
#705
1"
b0 0
b1100 /
b1000 6
b1111111 (
b1111111 .
1)
1'
b11011 ,
#707
b1 1
b1 -
b1110100 !
b1110100 2
b1 3
b1100 7
1%
1$
#710
0'
#714
0$
#715
b1 4
0)
1'
#716
b11100 ,
#720
0'
#721
b1100 8
0%
1$
#722
b10001 +
#725
0"
b1 5
1'
#728
0$
#730
0'
#735
1"
b1 0
b1101 /
b10 1
b11 -
b1001 6
b1110101 !
b1110101 2
b10 3
b10000001 (
b10000001 .
1)
1%
1'
1$
b11101 ,
#740
0'
#742
0$
#745
b11 4
0)
1'
#746
b11110 ,
#749
b1101 7
0%
1$
#750
b10010 +
0'
#755
0"
b11 5
1'
#756
0$
#760
0'
#763
b11 1
b10 -
b1110110 !
b1110110 2
b11 3
b1101 8
1%
1$
#765
b10 4
1'
#770
0'
0$
#775
b10 5
1'
#777
0%
1$
#778
b10011 +
#780
0'
#784
0$
#785
1'
#790
0'
#791
b100 1
b110 -
b1111000 !
b1111000 2
b100 3
1%
1$
#795
b110 4
1'
#798
0$
#800
0'
#805
b110 5
0%
1'
1$
#806
b10100 +
#810
0'
#812
0$
#815
1'
#819
b101 1
b111 -
b1111010 !
b1111010 2
b101 3
1%
1$
#820
0'
#825
b111 4
1'
#826
0$
#830
0'
#833
0%
1$
#834
b10101 +
#835
b111 5
1'
#840
0'
0$
#845
1'
#847
b110 1
b101 -
b1111011 !
b1111011 2
b110 3
1%
1$
#850
0'
#854
0$
#855
b101 4
1'
#860
0'
#861
0%
1$
#862
b10110 +
#865
b101 5
1'
#868
0$
#870
0'
#875
b111 1
b100 -
b1111101 !
b1111101 2
b111 3
1%
1'
1$
#880
0'
#882
0$
#885
b100 4
1'
#889
0%
1$
#890
b10111 +
0'
#895
b100 5
1'
#896
0$
#900
0'
#903
b0 1
b1100 -
b1111111 !
b1111111 2
b1000 3
1%
1$
#905
b1100 4
1'
#910
0'
0$
#915
b1100 5
1'
#917
0%
1$
#918
b11000 +
#920
0'
#924
0$
#925
1'
#930
0'
#931
b1 1
1#
b1101 -
b10000001 !
b10000001 2
b1001 3
1%
1$
#935
b1101 4
1'
#938
0$
#940
0'
#945
b1101 5
0%
1'
1$
#946
b11001 +
#950
0'
#952
0$
#955
1'
#959
1$
#960
0'
#965
1'
#966
0$
#969
b11010 +
#970
0'
#973
1$
#975
1'
#980
0'
0$
#983
b11011 +
#985
1'
#987
1$
#990
0'
#994
0$
#995
1'
#997
b11100 +
#1000
0'
#1001
1$
#1005
1'
#1008
0$
#1010
0'
#1011
b11101 +
#1015
1'
1$
#1020
0'
#1022
0$
#1025
b10 0
b1111 /
b1010 6
b11111 ,
b10000010 (
b10000010 .
1)
1'
b11110 +
#1029
b1111 7
1$
#1030
0'
#1035
0)
1'
#1036
0$
#1040
0'
#1043
0#
b1111 8
1$
#1045
b11 0
b1110 /
b1011 6
b100000 ,
b10000011 (
b10000011 .
1)
1'
#1050
0'
0$
#1055
0)
1'
#1057
b1110 7
1$
#1060
0'
#1064
0$
#1065
b100 0
b1010 /
b1100 6
b100001 ,
b10000100 (
b10000100 .
1)
1'
#1070
0'
#1071
b1110 8
b1010 7
1$
#1075
0)
1'
#1078
0$
#1080
0'
#1085
b101 0
b1011 /
b1101 6
b1010 8
b100010 ,
b10000101 (
b10000101 .
1)
1'
1$
#1090
0'
#1092
0$
#1095
0)
1'
#1099
b1011 7
1$
#1100
0'
#1105
b110 0
b1001 /
b1110 6
b100011 ,
b10000110 (
b10000110 .
1)
1'
#1106
0$
#1110
0'
#1113
b1011 8
b1001 7
1$
#1115
0)
1'
#1120
0'
0$
#1125
b111 0
b1000 /
b1111 6
b100100 ,
b10000111 (
b10000111 .
1)
1'
#1127
b1001 8
b1000 7
1$
#1130
0'
#1134
0$
#1135
0)
1'
#1140
0'
#1141
b1000 8
1$
#1145
b0 0
b0 /
b0 6
b100101 ,
b10001000 (
b10001000 .
1)
1'
#1148
0$
#1150
0'
#1155
b0 7
0)
1'
1$
#1160
0'
#1162
0$
#1165
1"
b1 0
b1 /
b1 6
b100110 ,
b10001001 (
b10001001 .
1)
1'
#1169
b0 8
b1 7
1$
#1170
0'
#1175
0)
1'
#1176
0$
#1180
0'
#1183
b10 1
b1111 -
b10000010 !
b10000010 2
b1010 3
b1 8
1%
1$
#1185
b1111 4
1'
#1190
0'
0$
#1195
0"
b1111 5
1'
#1197
0%
1$
#1200
0'
#1204
0$
#1205
1'
#1210
0'
#1211
b11 1
b1110 -
b10000011 !
b10000011 2
b1011 3
1%
1$
#1215
b1110 4
1'
#1218
0$
#1220
0'
#1225
b1110 5
0%
1'
1$
#1230
0'
#1232
0$
#1235
1'
#1239
b100 1
b1010 -
b10000100 !
b10000100 2
b1100 3
1%
1$
#1240
0'
#1245
b1010 4
1'
#1246
0$
#1250
0'
#1253
0%
1$
#1255
b1010 5
1'
#1260
0'
0$
#1265
1'
#1267
b101 1
b1011 -
b10000101 !
b10000101 2
b1101 3
1%
1$
#1270
0'
#1274
0$
#1275
b1011 4
1'
#1280
0'
#1281
0%
1$
#1285
b1011 5
1'
#1288
0$
#1290
0'
#1295
b110 1
b1001 -
b10000110 !
b10000110 2
b1110 3
1%
1'
1$
#1300
0'
#1302
0$
#1305
b1001 4
1'
#1309
0%
1$
#1310
0'
#1315
b1001 5
1'
#1316
0$
#1320
0'
#1323
b111 1
b1000 -
b10000111 !
b10000111 2
b1111 3
1%
1$
#1325
b1000 4
1'
#1330
0'
0$
#1335
b1000 5
1'
#1337
0%
1$
#1340
0'
#1344
0$
#1345
1'
#1350
0'
#1351
b0 1
b0 -
b10001000 !
b10001000 2
b0 3
1%
1$
#1355
b0 4
1'
#1358
0$
#1360
0'
#1365
b0 5
0%
1'
1$
#1370
0'
#1372
0$
#1375
1'
#1379
b1 1
1#
b1 -
b10001001 !
b10001001 2
b1 3
1%
1$
#1380
0'
#1385
b1 4
1'
#1386
0$
#1390
0'
#1393
0%
1$
#1395
b1 5
1'
